blockperf/__init__.py
blockperf/__main__.py
blockperf/app.py
blockperf/blocksamplegroup.py
blockperf/clientid.py
blockperf/config.py
blockperf/errors.py
blockperf/handler.py
blockperf/logging.py
blockperf/logreader.py
blockperf/utils.py
blockperf/apiclient/__init__.py
blockperf/apiclient/base.py
blockperf/apiclient/client.py
blockperf/apiclient/requests.py
blockperf/commands/__init__.py
blockperf/commands/run.py
blockperf/models/peer.py
blockperf/models/samples.py
blockperf/models/events/__init__.py
blockperf/models/events/base.py
blockperf/models/events/event.py
blockperf/models/events/peer.py
openblockperf-0.0.5.dist-info/licenses/LICENCE
openblockperf-0.0.5.dist-info/licenses/LICENSE
openblockperf-0.0.5.dist-info/METADATA
openblockperf-0.0.5.dist-info/WHEEL
openblockperf-0.0.5.dist-info/entry_points.txt
openblockperf-0.0.5.dist-info/top_level.txt
openblockperf-0.0.5.dist-info/RECORD
