Metadata-Version: 2.4
Name: openblockperf
Version: 0.0.5
Summary: The OpenBlockperf client
Author-email: Manuel Schmidt <manuel.schmidt@cardanofoundation.org>, Markus Gufler <markus.gufler-ext@cardanofoundation.org>
Maintainer-email: Manuel Schmidt <manuel.schmidt@cardanofoundation.org>, Markus Gufler <markus.gufler-ext@cardanofoundation.org>
Project-URL: Homepage, https://github.com/cardano-foundation/openblockperf
Project-URL: Bug Reports, https://github.com/cardano-foundation/openblockperf/issues
Keywords: cardano,cardano-foundation,ops
Requires-Python: >=3.12
License-File: LICENCE
License-File: LICENSE
Requires-Dist: click>=8.1.8
Requires-Dist: httpx>=0.28.1
Requires-Dist: loguru>=0.7.3
Requires-Dist: psutil>=7.1.0
Requires-Dist: pydantic>=2.10.6
Requires-Dist: pydantic-settings>=2.8.0
Requires-Dist: textual>=6.1.0
Requires-Dist: typer>=0.15.2
Dynamic: license-file
